ishelar/__init__.py
ishelar-0.1.0.dist-info/licenses/LICENSE
ishelar-0.1.0.dist-info/METADATA
ishelar-0.1.0.dist-info/WHEEL
ishelar-0.1.0.dist-info/top_level.txt
ishelar-0.1.0.dist-info/RECORD
