Metadata-Version: 2.4
Name: ishelar
Version: 0.1.0
Summary: Like antigravity, but opens your portfolio.
Home-page: https://www.saurhub.in/
Author: Saurabh Shelar
Author-email: mr.saurabhshelar@gmail.com
Classifier: Programming Language :: Python :: 3
Classifier: Operating System :: OS Independent
Classifier: Intended Audience :: Developers
Classifier: License :: OSI Approved :: MIT License
Classifier: Topic :: Utilities
Requires-Python: >=3.6
License-File: LICENSE
Dynamic: author
Dynamic: author-email
Dynamic: classifier
Dynamic: description
Dynamic: description-content-type
Dynamic: home-page
Dynamic: license-file
Dynamic: requires-python
Dynamic: summary
